pymarker/__init__.py
pymarker/cli.py
pymarker/core.py
pymarker/exceptions.py
pymarker/utils.py
pymarker-1.2.0.dist-info/LICENSE
pymarker-1.2.0.dist-info/METADATA
pymarker-1.2.0.dist-info/WHEEL
pymarker-1.2.0.dist-info/entry_points.txt
pymarker-1.2.0.dist-info/RECORD
