Metadata-Version: 2.1
Name: pymarker
Version: 1.2.0
Summary: A python package to generate AR markers and patterns based on input images
Home-page: https://github.com/pablodiegoss/pymarker
Keywords: AR,pattern,markers,jandig,hiro
Author: Pablo Silva
Author-email: pablodiegoss@hotmail.com
Requires-Python: >=3.10,<4.0
Classifier: Development Status :: 4 - Beta
Classifier: License :: OSI Approved :: GNU General Public License v3 (GPLv3)
Classifier: Operating System :: OS Independent
Classifier: Programming Language :: Python :: 3
Classifier: Programming Language :: Python :: 3.10
Classifier: Programming Language :: Python :: 3.11
Classifier: Programming Language :: Python :: 3.12
Classifier: Programming Language :: Python :: 3.13
Requires-Dist: click (>=8.2.1,<9.0.0)
Requires-Dist: pillow (>=11.3.0,<12.0.0)
Project-URL: Repository, https://github.com/pablodiegoss/pymarker
